{"name": "Kate Blumberg", "current role": "Real Estate Agent", "birth name": "Kathryn Mary Blumberg", "birth date": "1971-01-31", "birth place": "Cape Town, South Africa", "height": " ", "biography": "Kate Blumberg was born on January 31, 1971 in Cape Town, South Africa as Kathryn Mary Blumberg. She is an actress, known for The Big Short (2015) and Younger (2015). She is married to Todd Weeks.::Anonymous", "trade mark": " ", "trivia": ["Attended NYU Tisch School of the Arts and trained at the Atlantic Theater Company Acting School in New York City."], "filmography": ["Bull", "The Performance", "Blush", "Lethal Weapon", "Blue Bloods", "Younger", "This Is Us", "The Big Short", "The Night Shift", "Law & Order: Special Victims Unit", "Phil Spector", "inFamous 2", "CSI: Crime Scene Investigation", "Louie", "Ugly Betty", "We Pedal Uphill", "Law & Order: Criminal Intent (2006-2008)", "The Deal", "Choke", "The Cry", "Raving", "Medium", "Grey's Anatomy", "Whoopi", "Heartbreak Hospital", "Serendipity", "Picture This", "Colin Fitz Lives!"]}